odoo8_addon_account_invoice_production_lot-8.0.1.1.0.99.dev21-py2.7-nspkg.pth
odoo8_addon_account_invoice_production_lot-8.0.1.1.0.99.dev21.dist-info/METADATA
odoo8_addon_account_invoice_production_lot-8.0.1.1.0.99.dev21.dist-info/RECORD
odoo8_addon_account_invoice_production_lot-8.0.1.1.0.99.dev21.dist-info/WHEEL
odoo8_addon_account_invoice_production_lot-8.0.1.1.0.99.dev21.dist-info/namespace_packages.txt
odoo8_addon_account_invoice_production_lot-8.0.1.1.0.99.dev21.dist-info/top_level.txt
odoo_addons/account_invoice_production_lot/README.rst
odoo_addons/account_invoice_production_lot/__init__.py
odoo_addons/account_invoice_production_lot/__openerp__.py
odoo_addons/account_invoice_production_lot/invoice.py
odoo_addons/account_invoice_production_lot/invoice_view.xml
odoo_addons/account_invoice_production_lot/demo/sale.yml
odoo_addons/account_invoice_production_lot/i18n/account_invoice_production_lot.pot
odoo_addons/account_invoice_production_lot/i18n/bs.po
odoo_addons/account_invoice_production_lot/i18n/ca.po
odoo_addons/account_invoice_production_lot/i18n/cs.po
odoo_addons/account_invoice_production_lot/i18n/de.po
odoo_addons/account_invoice_production_lot/i18n/es.po
odoo_addons/account_invoice_production_lot/i18n/es_MX.po
odoo_addons/account_invoice_production_lot/i18n/fr.po
odoo_addons/account_invoice_production_lot/i18n/fr_CH.po
odoo_addons/account_invoice_production_lot/i18n/hr.po
odoo_addons/account_invoice_production_lot/i18n/hr_HR.po
odoo_addons/account_invoice_production_lot/i18n/it.po
odoo_addons/account_invoice_production_lot/i18n/nl_BE.po
odoo_addons/account_invoice_production_lot/i18n/nl_NL.po
odoo_addons/account_invoice_production_lot/i18n/pt_BR.po
odoo_addons/account_invoice_production_lot/i18n/pt_PT.po
odoo_addons/account_invoice_production_lot/i18n/sl.po
odoo_addons/account_invoice_production_lot/i18n/tr.po
odoo_addons/account_invoice_production_lot/i18n/tr_TR.po
odoo_addons/account_invoice_production_lot/static/description/icon.png
odoo_addons/account_invoice_production_lot/tests/__init__.py
odoo_addons/account_invoice_production_lot/tests/test_invoice_production_lot.py
odoo_addons/account_invoice_production_lot/view/report_invoice.xml
